data_finder-0.1.7.dist-info/licenses/LICENSE
datafinder/__init__.py
datafinder/attribute.py
datafinder/finder.py
datafinder/output.py
datafinder/runner.py
datafinder/sql_generator.py
datafinder/typed_attributes.py
datafinder_duckdb/__init__.py
datafinder_duckdb/duckdb_engine.py
datafinder_generator/generator.py
datafinder_generator/templates/finder_template.txt
datafinder_ibis/__init__.py
datafinder_ibis/ibis_engine.py
model/__init__.py
model/m3.py
model/mapping.py
model/milestoning.py
model/relational.py
model/relational_mapping.py
data_finder-0.1.7.dist-info/METADATA
data_finder-0.1.7.dist-info/WHEEL
data_finder-0.1.7.dist-info/top_level.txt
data_finder-0.1.7.dist-info/RECORD
